LICENSE
README.md
setup.py
scratchattach/__init__.py
scratchattach/cloud.py
scratchattach/cloud_requests.py
scratchattach/encoder.py
scratchattach/exceptions.py
scratchattach/forum.py
scratchattach/logger.py
scratchattach/project.py
scratchattach/session.py
scratchattach/studio.py
scratchattach/textcolors.py
scratchattach/user.py
scratchattach_pillow.egg-info/PKG-INFO
scratchattach_pillow.egg-info/SOURCES.txt
scratchattach_pillow.egg-info/dependency_links.txt
scratchattach_pillow.egg-info/requires.txt
scratchattach_pillow.egg-info/top_level.txt